{
    "data": [
        {
                "id": "17",
                "title": "Doccia",
                "slug": "Demo text here"
            },
            {
                "id": "24",
                "title": "Demo",
                "slug": "Demo text here"
            },
            {
                "id": "25",
                "title": "Demo 3",
                "slug": "Demo text here"
            },
            {
                "id": "26",
                "title": "Demo 4",
                "slug": "Demo text here"
            },
            {
                "id": "27",
                "title": "Doccia",
                "slug": "Demo text here"
            },
            {
                "id": "28",
                "title": "Doccia",
                "slug": "Demo text here"
            },
            {
                "id": "29",
                "title": "Doccia",
                "slug": "Demo text here"
            },
            {
                "id": "30",
                "title": "Doccia",
                "slug": "Demo text here"
            }
        ]
}